business_metrics.py
ranver_business_metrics-0.1.0.dist-info/METADATA
ranver_business_metrics-0.1.0.dist-info/WHEEL
ranver_business_metrics-0.1.0.dist-info/entry_points.txt
ranver_business_metrics-0.1.0.dist-info/top_level.txt
ranver_business_metrics-0.1.0.dist-info/RECORD
