Metadata-Version: 2.1
Name: ranver_business_metrics
Version: 0.1.0
Summary: calculate roi
